sfsimodels/__about__.py
sfsimodels/__init__.py
sfsimodels/build_model_descriptions.py
sfsimodels/checking_tools.py
sfsimodels/exceptions.py
sfsimodels/files.py
sfsimodels/functions.py
sfsimodels/loader.py
sfsimodels/models_data.dat
sfsimodels/output.py
sfsimodels/print_all_parameters.py
sfsimodels/properties.py
sfsimodels/scores.py
sfsimodels/sensors.py
sfsimodels/std.py
sfsimodels/methods/__init__.py
sfsimodels/methods/soils.py
sfsimodels/models/__init__.py
sfsimodels/models/abstract_models.py
sfsimodels/models/base_model.py
sfsimodels/models/buildings.py
sfsimodels/models/coordinates.py
sfsimodels/models/foundations.py
sfsimodels/models/hazards.py
sfsimodels/models/loads.py
sfsimodels/models/materials.py
sfsimodels/models/sections.py
sfsimodels/models/soils.py
sfsimodels/models/systems.py
sfsimodels/models/time.py
sfsimodels/models/units.py
sfsimodels/num/__init__.py
sfsimodels/num/mesh/__init__.py
sfsimodels/num/mesh/fns.py
sfsimodels/num/mesh/mesh2d_orth.py
sfsimodels/num/mesh/mesh2d_vary_y.py
sfsimodels-0.9.46.dist-info/LICENSE
sfsimodels-0.9.46.dist-info/METADATA
sfsimodels-0.9.46.dist-info/WHEEL
sfsimodels-0.9.46.dist-info/top_level.txt
sfsimodels-0.9.46.dist-info/RECORD
