Metadata-Version: 2.1
Name: sfsimodels
Version: 0.9.46
Summary: A set of standard models for assessing structural and geotechnical problems
Home-page: https://github.com/eng-tools/sfsimodels
Author: Maxim Millen
Author-email: mmi46@uclive.ac.nz
License: MIT
Keywords: geotechnical structural soil
Platform: UNKNOWN
Classifier: Development Status :: 3 - Alpha
Classifier: Intended Audience :: Science/Research
Classifier: Topic :: Scientific/Engineering
Classifier: License :: OSI Approved :: MIT License
Classifier: Programming Language :: Python :: 3
Requires-Python: >=3.3
License-File: LICENSE
Requires-Dist: numpy (>=1.7)
Provides-Extra: test
Requires-Dist: pytest ; extra == 'test'
